oidv6_to_voc/__init__.py
oidv6_to_voc/__main__.py
oidv6_to_voc-0.1.5.dist-info/LICENSE
oidv6_to_voc-0.1.5.dist-info/METADATA
oidv6_to_voc-0.1.5.dist-info/WHEEL
oidv6_to_voc-0.1.5.dist-info/entry_points.txt
oidv6_to_voc-0.1.5.dist-info/top_level.txt
oidv6_to_voc-0.1.5.dist-info/RECORD
