Metadata-Version: 2.1
Name: oidv6-to-voc
Version: 0.1.5
Summary: Convert Open Images Dataset v6 to PASCAL VOC format.
Home-page: https://github.com/chuangzhu/oidv6-to-voc/
Author: Zhu Chuang
Author-email: genelocated@yandex.com
License: UNKNOWN
Platform: UNKNOWN
Requires-Dist: Pillow (>=6.2.1)
